{
    "_preset"     : "AllOn",
    "_author"     : "Danilo Pinheiro",
    "_date"       : "2022-09-12",
    "_updated"    : "2023-05-05",

    "DuplicatedName"            : true,
    "FreezeTransform"           : true,
    "ImportReference"           : true,
    "NamespaceCleaner"          : true,
    "ShowBPCleaner"             : true,
    "UnlockInitialShadingGroup" : true,
    "VaccineCleaner"            : true,

    "BrokenNetCleaner"          : true,
    "ColorSetCleaner"           : true,
    "DisplayLayers"             : true,
    "ExitEditMode"              : true,
    "HideCorrectives"           : true,
    "HideDataGrp"               : true,
    "KeyframeCleaner"           : true,
    "NgSkinToolsCleaner"        : true,
    "ResetPose"                 : true,
    "SideCalibration"           : true,
    "TargetCleaner"             : true,
    "WIPCleaner"                : true
}